cerise_manager/__init__.py
cerise_manager/__version__.py
cerise_manager/errors.py
cerise_manager/service.py
cerise_manager-0.3.1.dist-info/LICENSE
cerise_manager-0.3.1.dist-info/METADATA
cerise_manager-0.3.1.dist-info/NOTICE
cerise_manager-0.3.1.dist-info/WHEEL
cerise_manager-0.3.1.dist-info/top_level.txt
cerise_manager-0.3.1.dist-info/RECORD
