Metadata-Version: 2.1
Name: cerise-manager
Version: 0.3.1
Summary: A manager for containerised Cerise instances
Home-page: https://github.com/MD-Studio/cerise_manager
Author: Lourens Veen
Author-email: l.veen@esciencecenter.nl
License: Apache Software License 2.0
Keywords: cerise_manager
Platform: UNKNOWN
Classifier: Development Status :: 2 - Pre-Alpha
Classifier: Intended Audience :: Developers
Classifier: License :: OSI Approved :: Apache Software License
Classifier: Natural Language :: English
Classifier: Programming Language :: Python :: 3
Classifier: Programming Language :: Python :: 3.4
Classifier: Programming Language :: Python :: 3.5
Classifier: Programming Language :: Python :: 3.6
Requires-Dist: cerise-client (>=0.3.0)
Requires-Dist: defusedxml (==0.5.0)
Requires-Dist: docker (<4)
Requires-Dist: future
Requires-Dist: idna (<2.8)
Provides-Extra: dev
Requires-Dist: prospector[with_pyroma] ; extra == 'dev'
Requires-Dist: yapf ; extra == 'dev'
Requires-Dist: isort ; extra == 'dev'
